README.md
setup.py
defectfinder/__init__.py
defectfinder/classactmap.py
defectfinder/extract_predict.py
defectfinder/preprocessing.py
defectfinder/version.py
defectfinder.egg-info/PKG-INFO
defectfinder.egg-info/SOURCES.txt
defectfinder.egg-info/dependency_links.txt
defectfinder.egg-info/requires.txt
defectfinder.egg-info/top_level.txt
defectfinder/tests/__init__.py
defectfinder/tests/pathmagic.py
defectfinder/tests/test_classactmap.py
defectfinder/tests/test_preprocessing.py
dm3_lib/__init__.py
dm3_lib/_dm3_lib.py