Metadata-Version: 1.2
Name: defectfinder
Version: 0.1
Summary: defectfinder: finds and predicts defect types
Home-page: https://github.com/SarthakJariwala/DLSSTRP
Author: SARTHAK
Author-email: jariwala@uw.edu
Maintainer: Sarthak
Maintainer-email: jariwala@uw.edu
License: MIT
Platform: OS Independent
Classifier: Development Status :: 3 - Alpha
Classifier: Environment :: Console
Classifier: Intended Audience :: Science/Research
Classifier: License :: OSI Approved :: MIT License
Classifier: Operating System :: OS Independent
Classifier: Programming Language :: Python
Classifier: Topic :: Scientific/Engineering
